ultragpt/__init__.py
ultragpt/config/__init__.py
ultragpt/config/config.py
ultragpt/core/__init__.py
ultragpt/core/chat_flow.py
ultragpt/core/core.py
ultragpt/core/pipelines.py
ultragpt/messaging/__init__.py
ultragpt/messaging/history_utils.py
ultragpt/messaging/message_ops.py
ultragpt/messaging/token_manager.py
ultragpt/messaging/token_limits/__init__.py
ultragpt/messaging/token_limits/langchain_limiter.py
ultragpt/prompts/__init__.py
ultragpt/prompts/prompts.py
ultragpt/providers/__init__.py
ultragpt/providers/_langchain_patches.py
ultragpt/providers/providers.py
ultragpt/schemas/__init__.py
ultragpt/schemas/schema_utils.py
ultragpt/schemas/tool_schemas.py
ultragpt/tooling/__init__.py
ultragpt/tooling/tools_manager.py
ultragpt/tools/__init__.py
ultragpt/tools/calculator/__init__.py
ultragpt/tools/calculator/core.py
ultragpt/tools/calculator/prompts.py
ultragpt/tools/calculator/schemas.py
ultragpt/tools/math_operations/__init__.py
ultragpt/tools/math_operations/core.py
ultragpt/tools/math_operations/prompts.py
ultragpt/tools/math_operations/schemas.py
ultragpt/tools/web_search/__init__.py
ultragpt/tools/web_search/context.py
ultragpt/tools/web_search/core.py
ultragpt/tools/web_search/prompts.py
ultragpt/tools/web_search/schemas.py
ultragpt-7.1.0.dist-info/licenses/LICENSE.rst
ultragpt-7.1.0.dist-info/METADATA
ultragpt-7.1.0.dist-info/WHEEL
ultragpt-7.1.0.dist-info/top_level.txt
ultragpt-7.1.0.dist-info/RECORD
