Metadata-Version: 2.4
Name: ultragpt
Version: 7.1.0
Summary: UltraGPT: A modular multi-provider AI library for advanced reasoning and step pipelines with OpenAI and Claude support
Home-page: https://github.com/Kawai-Senpai/UltraGPT
Author: Ranit Bhowmick
Author-email: mail@ranitbhowmick.com
License: MIT
Project-URL: Bug Reports, https://github.com/Kawai-Senpai/UltraGPT/issues
Project-URL: Source, https://github.com/Kawai-Senpai/UltraGPT
Project-URL: Documentation, https://github.com/Kawai-Senpai/UltraGPT/tree/main/docs
Keywords: ai,gpt,openai,claude,anthropic,reasoning,pipeline,tools,multi-provider
Classifier: Development Status :: 4 - Beta
Classifier: Intended Audience :: Developers
Classifier: License :: OSI Approved :: MIT License
Classifier: Programming Language :: Python :: 3
Classifier: Programming Language :: Python :: 3.6
Classifier: Programming Language :: Python :: 3.7
Classifier: Programming Language :: Python :: 3.8
Classifier: Programming Language :: Python :: 3.9
Classifier: Programming Language :: Python :: 3.10
Classifier: Programming Language :: Python :: 3.11
Classifier: Programming Language :: Python :: 3.12
Classifier: Topic :: Software Development :: Libraries :: Python Modules
Classifier: Topic :: Scientific/Engineering :: Artificial Intelligence
Requires-Python: >=3.6
License-File: LICENSE.rst
Requires-Dist: pydantic>=2.10.4
Requires-Dist: langchain-core>=1.0.1
Requires-Dist: langchain-openai>=1.0.1
Requires-Dist: langchain-anthropic>=1.0.0
Requires-Dist: ultraprint>=3.5.0
Requires-Dist: google-api-python-client>=2.0.0
Requires-Dist: requests>=2.25.0
Requires-Dist: beautifulsoup4>=4.9.0
Requires-Dist: readability-lxml>=0.8.0
Requires-Dist: lxml>=4.6.0
Provides-Extra: env
Requires-Dist: python-dotenv>=0.19.0; extra == "env"
Provides-Extra: dev
Requires-Dist: pytest>=6.0; extra == "dev"
Requires-Dist: pytest-cov>=2.0; extra == "dev"
Provides-Extra: all
Requires-Dist: python-dotenv>=0.19.0; extra == "all"
Dynamic: author
Dynamic: author-email
Dynamic: classifier
Dynamic: description
Dynamic: description-content-type
Dynamic: home-page
Dynamic: keywords
Dynamic: license
Dynamic: license-file
Dynamic: project-url
Dynamic: provides-extra
Dynamic: requires-dist
Dynamic: requires-python
Dynamic: summary
